zoek/__init__.py
zoek/_custom_operators.py
zoek/_filter_attr.py
zoek/cli.py
zoek/generator_from_path.py
zoek/print_iterable.py
zoek-0.0.2.dist-info/LICENSE
zoek-0.0.2.dist-info/METADATA
zoek-0.0.2.dist-info/WHEEL
zoek-0.0.2.dist-info/entry_points.txt
zoek-0.0.2.dist-info/top_level.txt
zoek-0.0.2.dist-info/RECORD
